LICENSE.md
MANIFEST.in
README.md
setup.cfg
setup.py
geostatil/__init__.py
geostatil/geostatil.py
geostatil.egg-info/PKG-INFO
geostatil.egg-info/SOURCES.txt
geostatil.egg-info/dependency_links.txt
geostatil.egg-info/namespace_packages.txt
geostatil.egg-info/not-zip-safe
geostatil.egg-info/requires.txt
geostatil.egg-info/top_level.txt
geostatil/data/crs.json
geostatil/data/geometries.json
geostatil/data/stat-data.json