Metadata-Version: 1.1
Name: geostatil
Version: 0.0.1
Summary: Detailed statistical data on any point in Israel
Home-page: https://github.com/akariv/geostatil
Author: Adam Kariv
Author-email: adam@obudget.org
License: MIT
Keywords: cbs lamas statistics israel
Platform: UNKNOWN
Classifier: Development Status :: 3 - Alpha
Classifier: Intended Audience :: Developers
Classifier: License :: OSI Approved :: MIT License
Classifier: Operating System :: OS Independent
Classifier: Programming Language :: Python :: 2.6
Classifier: Programming Language :: Python :: 2.7
Classifier: Programming Language :: Python :: 3.3
Classifier: Programming Language :: Python :: 3.4
